{
    "Dashboard": "Dashboard",
    "Contractors": "Mga kontratista",
    "Roles": "Mga tungkulin",
    "Welcome": "Maligayang pagdating",
    "profile": "Profile",
    "Registrations": "Mga pagpaparehistro",
    "Years": "Pagsala ng Taon",
    "Activites": "Mga aktibidad",
    "subscription": "Bagong subscription",
    "newSubs": "Nakakuha ka ng bagong subscription I-tap para tingnan",
    "earning": "Kabuuang Kita",
    "Subscribers": "Kabuuang mga Subscriber",
    "Vendors": "Kabuuang mga Vendor",
    "manger": "General Manger",
    "Marketing": "Mga Tagapamahala ng Marketing",
    "leaders": "Pinuno ng pangkat",
    "spv": "Mga superbisor",
    "agent": "Mga ahente",
    "Regestrations": "Mga regestration",
    "Today": "Ngayong araw",
    "Last_Week": "nakaraang linggo",
    "Last_Month": "Noong nakaraang buwan",
    "Last_3_Months": "huling 3 buwan",
    "view": "isang alok",
    "January": "Enero",
    "February": "Pebrero",
    "March": "Marso",
    "April": "Abril",
    "May": "mayo",
    "June": "Si Jun",
    "July": "Hulyo",
    "Aug": "Agosto",
    "Sept": "Setyembre",
    "Oct": "Oktubre",
    "Nov": "Nob",
    "Dec": "Dec",
    "Next": "kasunod",
    "previous": "Nakaraang",
    "Joined": "sumali",
    "Online": "Nakakonekta",
    "offline": "hindi konektado",
    "Active": "Masigla",
    "InActive": "Hindi aktibo",
    "Contracts": "mga kontrata",
    "view_all": "Tingnan lahat ",
    "Search": "paghahanap",
    "vendors": "mga nagtitinda",
    "Language": "Wika",
  "Birthdate": "Araw ng kapanganakan",
  "Country": "Bansa",
  "City": "lungsod",
  "Phone_Number": "Numero ng telepono",
  "Change_Password": "Palitan ANG password",
  "Privacy_Policy": "Patakaran sa Privacy",
  "Terms_Condtions": "Mga Tuntunin at Kundisyon",
  "Accounts_Deleted": "Mga Account na Tinanggal",
  "Accounts_Locked": "Naka-lock ang Mga Account",
  "E-mails": "Mga email",
  "Commercial_info": "Komersyal na impormasyon",
  "Commercial": "Komersyal",
  "Entity": "Entidad",
  "Tax": "Buwis",
  "Social_Links": "Mga Social Link",
  "Facebook": "Facebook",
  "Website": "Website",
  "Twitter": "Twitter",
  "Linkedin": "Linkin",
  "instagram": "instagram",
  "restore": "Ibalik",
  "unlock": "I-unlock",
  "Contact": "Makipag-ugnayan",
  "Sales": "Benta",
  "Recruitment": "Recruitment",
  "unblock_Warning": "hindi mo ito magagawa sa pamamagitan ng dashboard, mangyaring gawin ito gamit ang mobile app",
  "userData": "hindi Magagamit ang data ng user",
  "noBranches": "Wala pang mga Branch",
  "Brancehs": "Mga branch",
  "Name": "Pangalan",
  "Code": "Code",
  "Subscribtion": "Mga araw ng subscription",
  "Package": "Presyo ng Package",
  "Description": "Paglalarawan",
  "Agencies": "Mga ahensya",
  "updates": "mayroon kaming mga update at aayusin namin ito sa lalong madaling panahon",
  "userAvail": "Hindi Magagamit ang User",
  "confirmed": "Hindi pa Nakumpirma",
  "cancel": "Kanselahin",
  "Logout": "Mag-logout",
  "Password": "password",
  "New_Password": "Bagong password",
  "Confirm_New_Password": "Kumpirmahin ang bagong password",
  "Confirm": "Kumpirmahin",
  "id": "User ID",
  "No_Agents": "Walang Ahente",
  "No_Branches": "Wala pang Branch",
  "No_Links": "Wala pang Link",
  "from": "mula sa",
  "to": "sa"
  }